COPYING.rst
MANIFEST.in
README.rst
sendlib.py
setup.py
doc/api.rst
doc/conf.py
doc/designobjectives.rst
doc/index.rst
doc/tutorial.rst
sendlib.egg-info/PKG-INFO
sendlib.egg-info/SOURCES.txt
sendlib.egg-info/dependency_links.txt
sendlib.egg-info/top_level.txt
sendlib.egg-info/zip-safe
test/test_data.py
test/test_parse.py
test/test_serialize.py