Metadata-Version: 1.0
Name: sendlib
Version: 0.2.1
Summary: sendlib  is a lightweight message serialization library which aims to be memory efficient
Home-page: http://github.com/dcrosta/sendlib
Author: Daniel Crosta
Author-email: dcrosta@late.am
License: UNKNOWN
Keywords: message serialization
Platform: UNKNOWN
Classifier: Programming Language :: Python
Classifier: Programming Language :: Python :: 2.6
Classifier: Programming Language :: Python :: 2.7
Classifier: Topic :: Software Development
Classifier: Topic :: Software Development :: Libraries
Classifier: License :: OSI Approved :: BSD License
Classifier: Development Status :: 4 - Beta
